freedev/__init__.py
freedev-1.1.2.dist-info/METADATA
freedev-1.1.2.dist-info/WHEEL
freedev-1.1.2.dist-info/top_level.txt
freedev-1.1.2.dist-info/RECORD
