Metadata-Version: 2.4
Name: freedev
Version: 1.1.2
Summary: This is a library for password-protected decryption using opn. I created it to surprise my friend for his birthday. Please don't delete it
Author: coorton202
Author-email: coorton50@gmail.com
Classifier: Programming Language :: Python :: 3
Classifier: Operating System :: OS Independent
Requires-Python: >=3.6
Dynamic: author
Dynamic: author-email
Dynamic: classifier
Dynamic: requires-python
Dynamic: summary
